{"assets":{"38D2CCA2A1F194D662E48EE5EE84E43D":{"type":"texture","index":19,"assetRequest":{"type":"slide","state":"incoming","slide":"E698643A-E478-4218-8DA7-86CC194D9BB3"},"url":{"web":"assets/38D2CCA2A1F194D662E48EE5EE84E43D.svg"},"width":720,"height":540},"E6C15740167D035632F4982C76B9F4ED":{"type":"texture","index":18,"assetRequest":{"type":"slide","state":"outgoing","slide":"2895B78F-B506-427F-B370-618E2975D380"},"url":{"web":"assets/E6C15740167D035632F4982C76B9F4ED.svg"},"width":720,"height":540}},"events":[{"effects":[{"beginTime":0,"baseLayer":{"animations":[],"initialState":{"affineTransform":[1,0,0,1,0,0],"masksToBounds":false,"rotation":0,"scale":1,"position":{"pointX":360,"pointY":270},"width":720,"sublayerTransform":[1,0,0,0,0,1,0,0,0,0,1,0,0,0,0,1],"contentsRect":{"y":0,"x":0,"width":1,"height":1},"opacity":1,"edgeAntialiasingMask":251658240,"height":540,"hidden":false,"anchorPoint":{"pointX":0.5,"pointY":0.5}},"objectID":"0","layers":[{"animations":[],"initialState":{"affineTransform":[1,0,0,1,0,0],"masksToBounds":false,"rotation":0,"scale":1,"position":{"pointX":360,"pointY":270},"width":720,"sublayerTransform":[1,0,0,0,0,1,0,0,0,0,1,-0.0007001582493355197,0,0,0,1],"contentsRect":{"y":0,"x":0,"width":1,"height":1},"opacity":1,"edgeAntialiasingMask":251658240,"height":540,"hidden":false,"anchorPoint":{"pointX":0.5,"pointY":0.5}},"layers":[{"animations":[],"layers":[],"initialState":{"affineTransform":[1,0,0,1,0,0],"masksToBounds":false,"rotation":0,"scale":1,"position":{"pointX":360,"pointY":270},"width":720,"sublayerTransform":[1,0,0,0,0,1,0,0,0,0,1,0,0,0,0,1],"contentsRect":{"y":0,"x":0,"width":1,"height":1},"opacity":1,"edgeAntialiasingMask":0,"height":540,"hidden":false,"anchorPoint":{"pointX":0.5,"pointY":0.5}},"texture":"38D2CCA2A1F194D662E48EE5EE84E43D"},{"animations":[{"timeOffset":0,"from":{"scalar":false},"beginTime":0,"repeatCount":0,"fillMode":"both","property":"hidden","autoreverses":false,"duration":0.01,"to":{"scalar":true}}],"layers":[],"initialState":{"affineTransform":[1,0,0,1,0,0],"masksToBounds":false,"rotation":0,"scale":1,"position":{"pointX":360,"pointY":270},"width":720,"sublayerTransform":[1,0,0,0,0,1,0,0,0,0,1,0,0,0,0,1],"contentsRect":{"y":0,"x":0,"width":1,"height":1},"opacity":1,"edgeAntialiasingMask":0,"height":540,"hidden":false,"anchorPoint":{"pointX":0.5,"pointY":0.5}},"texture":"E6C15740167D035632F4982C76B9F4ED"}]}]},"effects":[],"duration":0.01,"type":"transition","name":"none","objectID":"0"}],"automaticPlay":false,"hyperlinks":[],"accessibility":[{"text":"App Concerns: Front-End Implementation","targetRectangle":{"y":69.59999990463257,"x":21.59999990463257,"width":667.810546875,"height":42}},{"text":"use all the things!!1","targetRectangle":{"y":135.5984251499176,"x":32.1013548374176,"width":268.3154296875,"height":35}},{"text":"build for deployment","targetRectangle":{"y":170.5984251499176,"x":32.1013548374176,"width":283.2275390625,"height":35}},{"text":"profit","targetRectangle":{"y":205.5984251499176,"x":32.1013548374176,"width":76.0107421875,"height":35}},{"text":"caveats:","targetRectangle":{"y":345.5984251499176,"x":21.5984251499176,"width":112.4853515625,"height":35}},{"text":"know what you’re doing","targetRectangle":{"y":380.5984251499176,"x":57.59842586517334,"width":322.5732421875,"height":35}},{"text":"don’t obliterate WebContent/WEB-INF/","targetRectangle":{"y":415.5984251499176,"x":57.59842586517334,"width":545.625,"height":35}}],"baseLayer":{"animations":[],"initialState":{"affineTransform":[1,0,0,1,0,0],"masksToBounds":false,"rotation":0,"scale":1,"position":{"pointX":360,"pointY":270},"width":720,"sublayerTransform":[1,0,0,0,0,1,0,0,0,0,1,0,0,0,0,1],"contentsRect":{"y":0,"x":0,"width":1,"height":1},"opacity":1,"edgeAntialiasingMask":251658240,"height":540,"hidden":false,"anchorPoint":{"pointX":0.5,"pointY":0.5}},"objectID":"0","layers":[{"animations":[],"initialState":{"affineTransform":[1,0,0,1,0,0],"masksToBounds":false,"rotation":0,"scale":1,"position":{"pointX":360,"pointY":270},"width":720,"sublayerTransform":[1,0,0,0,0,1,0,0,0,0,1,-0.0007001582493355197,0,0,0,1],"contentsRect":{"y":0,"x":0,"width":1,"height":1},"opacity":1,"edgeAntialiasingMask":251658240,"height":540,"hidden":false,"anchorPoint":{"pointX":0.5,"pointY":0.5}},"layers":[{"animations":[],"layers":[],"initialState":{"affineTransform":[1,0,0,1,0,0],"masksToBounds":false,"rotation":0,"scale":1,"position":{"pointX":360,"pointY":270},"width":720,"sublayerTransform":[1,0,0,0,0,1,0,0,0,0,1,0,0,0,0,1],"contentsRect":{"y":0,"x":0,"width":1,"height":1},"opacity":1,"edgeAntialiasingMask":0,"height":540,"hidden":false,"anchorPoint":{"pointX":0.5,"pointY":0.5}},"texture":"E6C15740167D035632F4982C76B9F4ED"}]}]}}]}